{
  "fecha": "2026-02-09T03:49:08.534668",
  "experiment": "JADE v8.2 \u2014 El Puente (4070 Edition)",
  "question": "\u00bfEs el universo un canal de despolarizaci\u00f3n global?",
  "phase_completed": "phase1_partial",
  "gamma_jade": 0.6321205588285577,
  "results": {
    "config": {
      "max_hours": 6,
      "n_samples": 200,
      "scaling_configs": [
        [
          2,
          10
        ],
        [
          3,
          9
        ],
        [
          4,
          8
        ]
      ],
      "couplings": [
        "local",
        "random"
      ],
      "times": [
        5.0,
        10.0,
        20.0
      ],
      "n_realizations": 3
    },
    "phase1": [
      {
        "n_S": 2,
        "n_E": 1,
        "d_S": 4,
        "d_E": 2,
        "d_total": 8,
        "coupling": "local",
        "realization": 0,
        "t": 5.0,
        "seed": 2100,
        "C_mean": 0.35392823131898254,
        "C_std": 0.08414660107781959,
        "gamma_eff": 0.8681989618784232,
        "D_best": 0.3519939449115301,
        "D_best_std": 0.054814679253958866,
        "D_jade": 0.366893616977905,
        "D_jade_std": 0.05574403174725758,
        "elapsed": 0.5797207355499268
      },
      {
        "n_S": 2,
        "n_E": 1,
        "d_S": 4,
        "d_E": 2,
        "d_total": 8,
        "coupling": "local",
        "realization": 0,
        "t": 10.0,
        "seed": 2100,
        "C_mean": 0.4187261046491278,
        "C_std": 0.10436027403951244,
        "gamma_eff": 0.7882875030622077,
        "D_best": 0.39364587236384424,
        "D_best_std": 0.04493305617563941,
        "D_jade": 0.403353529851549,
        "D_jade_std": 0.058407539720576926,
        "elapsed": 0.5043697357177734
      },
      {
        "n_S": 2,
        "n_E": 1,
        "d_S": 4,
        "d_E": 2,
        "d_total": 8,
        "coupling": "local",
        "realization": 0,
        "t": 20.0,
        "seed": 2100,
        "C_mean": 0.23685817650995553,
        "C_std": 0.12232408334210844,
        "gamma_eff": 1.0328977189810646,
        "D_best": 0.44219250407970134,
        "D_best_std": 0.07132837300059876,
        "D_jade": 0.49483573189132785,
        "D_jade_std": 0.07981247431408028,
        "elapsed": 0.5008676052093506
      },
      {
        "n_S": 2,
        "n_E": 1,
        "d_S": 4,
        "d_E": 2,
        "d_total": 8,
        "coupling": "random",
        "realization": 0,
        "t": 5.0,
        "seed": 2100,
        "C_mean": 0.32140666470285467,
        "C_std": 0.10775785354362379,
        "gamma_eff": 0.9204224333325799,
        "D_best": 0.4297046056157447,
        "D_best_std": 0.06436104524319955,
        "D_jade": 0.46448952913373726,
        "D_jade_std": 0.07025376129760073,
        "elapsed": 0.5011312961578369
      },
      {
        "n_S": 2,
        "n_E": 1,
        "d_S": 4,
        "d_E": 2,
        "d_total": 8,
        "coupling": "random",
        "realization": 0,
        "t": 10.0,
        "seed": 2100,
        "C_mean": 0.24149263154812634,
        "C_std": 0.13866023210661327,
        "gamma_eff": 0.988289570650398,
        "D_best": 0.5776111847201923,
        "D_best_std": 0.04383787145344429,
        "D_jade": 0.615278094974707,
        "D_jade_std": 0.0568029326237451,
        "elapsed": 0.503227710723877
      },
      {
        "n_S": 2,
        "n_E": 1,
        "d_S": 4,
        "d_E": 2,
        "d_total": 8,
        "coupling": "random",
        "realization": 0,
        "t": 20.0,
        "seed": 2100,
        "C_mean": 0.31775245839855637,
        "C_std": 0.14387598949334826,
        "gamma_eff": 0.8985383131582386,
        "D_best": 0.47181137918305766,
        "D_best_std": 0.04361327514935483,
        "D_jade": 0.5159824804894807,
        "D_jade_std": 0.06563728059124073,
        "elapsed": 0.5013217926025391
      },
      {
        "n_S": 2,
        "n_E": 1,
        "d_S": 4,
        "d_E": 2,
        "d_total": 8,
        "coupling": "random",
        "realization": 1,
        "t": 5.0,
        "seed": 2101,
        "C_mean": 0.4050936407416774,
        "C_std": 0.10608653199897507,
        "gamma_eff": 0.7990614574602235,
        "D_best": 0.4757760233351931,
        "D_best_std": 0.052083865239221774,
        "D_jade": 0.4789418693813866,
        "D_jade_std": 0.06615038401322323,
        "elapsed": 0.5035724639892578
      },
      {
        "n_S": 2,
        "n_E": 1,
        "d_S": 4,
        "d_E": 2,
        "d_total": 8,
        "coupling": "random",
        "realization": 1,
        "t": 10.0,
        "seed": 2101,
        "C_mean": 0.30750915010193813,
        "C_std": 0.0903843463104847,
        "gamma_eff": 0.9299947925336475,
        "D_best": 0.3811943568024336,
        "D_best_std": 0.046920544086423904,
        "D_jade": 0.40375373814312426,
        "D_jade_std": 0.06748903920388108,
        "elapsed": 0.5078418254852295
      },
      {
        "n_S": 2,
        "n_E": 1,
        "d_S": 4,
        "d_E": 2,
        "d_total": 8,
        "coupling": "random",
        "realization": 1,
        "t": 20.0,
        "seed": 2101,
        "C_mean": 0.3118852221795316,
        "C_std": 0.12266641587737141,
        "gamma_eff": 0.9322159565971173,
        "D_best": 0.47702693982724936,
        "D_best_std": 0.04323290757219874,
        "D_jade": 0.5060133924114977,
        "D_jade_std": 0.054074560312573544,
        "elapsed": 0.5026512145996094
      },
      {
        "n_S": 2,
        "n_E": 1,
        "d_S": 4,
        "d_E": 2,
        "d_total": 8,
        "coupling": "random",
        "realization": 2,
        "t": 5.0,
        "seed": 2102,
        "C_mean": 0.5058023021855422,
        "C_std": 0.0777902696309246,
        "gamma_eff": 0.6799343599203844,
        "D_best": 0.3484644245659886,
        "D_best_std": 0.06515601959260764,
        "D_jade": 0.35051657796536917,
        "D_jade_std": 0.06725522763895432,
        "elapsed": 0.5049796104431152
      },
      {
        "n_S": 2,
        "n_E": 1,
        "d_S": 4,
        "d_E": 2,
        "d_total": 8,
        "coupling": "random",
        "realization": 2,
        "t": 10.0,
        "seed": 2102,
        "C_mean": 0.4535119460630422,
        "C_std": 0.19321578812561754,
        "gamma_eff": 0.7025903719218888,
        "D_best": 0.5840616375328893,
        "D_best_std": 0.062153467098731,
        "D_jade": 0.5707843428675379,
        "D_jade_std": 0.07224914439115446,
        "elapsed": 0.5037343502044678
      },
      {
        "n_S": 2,
        "n_E": 1,
        "d_S": 4,
        "d_E": 2,
        "d_total": 8,
        "coupling": "random",
        "realization": 2,
        "t": 20.0,
        "seed": 2102,
        "C_mean": 0.5396044350514977,
        "C_std": 0.10197348209344126,
        "gamma_eff": 0.5988788091407149,
        "D_best": 0.41736792914038323,
        "D_best_std": 0.05294999150889012,
        "D_jade": 0.42306062997281374,
        "D_jade_std": 0.05161781334800653,
        "elapsed": 0.4967055320739746
      },
      {
        "n_S": 2,
        "n_E": 2,
        "d_S": 4,
        "d_E": 4,
        "d_total": 16,
        "coupling": "local",
        "realization": 0,
        "t": 5.0,
        "seed": 2200,
        "C_mean": 0.24378112520247494,
        "C_std": 0.09403019597961208,
        "gamma_eff": 1.0033670147962526,
        "D_best": 0.3802993243500616,
        "D_best_std": 0.04139049050923385,
        "D_jade": 0.4462950935091652,
        "D_jade_std": 0.06452394677980221,
        "elapsed": 0.5393483638763428
      },
      {
        "n_S": 2,
        "n_E": 2,
        "d_S": 4,
        "d_E": 4,
        "d_total": 16,
        "coupling": "local",
        "realization": 0,
        "t": 10.0,
        "seed": 2200,
        "C_mean": 0.5030346059049158,
        "C_std": 0.06162638485279678,
        "gamma_eff": 0.7058388681991246,
        "D_best": 0.17317744225750403,
        "D_best_std": 0.03501933699922332,
        "D_jade": 0.17434020150865925,
        "D_jade_std": 0.02846354724942631,
        "elapsed": 0.5492515563964844
      },
      {
        "n_S": 2,
        "n_E": 2,
        "d_S": 4,
        "d_E": 4,
        "d_total": 16,
        "coupling": "local",
        "realization": 0,
        "t": 20.0,
        "seed": 2200,
        "C_mean": 0.35533812032842055,
        "C_std": 0.08260234783081993,
        "gamma_eff": 0.8533774117623679,
        "D_best": 0.25497916595795106,
        "D_best_std": 0.04657334696876259,
        "D_jade": 0.28457063613545214,
        "D_jade_std": 0.05086019308524586,
        "elapsed": 0.556525468826294
      },
      {
        "n_S": 2,
        "n_E": 2,
        "d_S": 4,
        "d_E": 4,
        "d_total": 16,
        "coupling": "random",
        "realization": 0,
        "t": 5.0,
        "seed": 2200,
        "C_mean": 0.3664651148117601,
        "C_std": 0.10952217216536268,
        "gamma_eff": 0.849507445488768,
        "D_best": 0.36720501702348574,
        "D_best_std": 0.06419418792381167,
        "D_jade": 0.3867353757082618,
        "D_jade_std": 0.07287007334282311,
        "elapsed": 0.557441234588623
      },
      {
        "n_S": 2,
        "n_E": 2,
        "d_S": 4,
        "d_E": 4,
        "d_total": 16,
        "coupling": "random",
        "realization": 0,
        "t": 10.0,
        "seed": 2200,
        "C_mean": 0.37649890210259174,
        "C_std": 0.06740032346937369,
        "gamma_eff": 0.814671292828188,
        "D_best": 0.27412695164068607,
        "D_best_std": 0.04524419424845345,
        "D_jade": 0.3031864571242987,
        "D_jade_std": 0.044451782660063124,
        "elapsed": 0.5621740818023682
      },
      {
        "n_S": 2,
        "n_E": 2,
        "d_S": 4,
        "d_E": 4,
        "d_total": 16,
        "coupling": "random",
        "realization": 0,
        "t": 20.0,
        "seed": 2200,
        "C_mean": 0.34129894687612333,
        "C_std": 0.10770705636981014,
        "gamma_eff": 0.8419700521472239,
        "D_best": 0.29999058758521546,
        "D_best_std": 0.04554014176238738,
        "D_jade": 0.3386036023239768,
        "D_jade_std": 0.04943379615235338,
        "elapsed": 0.5901768207550049
      },
      {
        "n_S": 2,
        "n_E": 2,
        "d_S": 4,
        "d_E": 4,
        "d_total": 16,
        "coupling": "random",
        "realization": 1,
        "t": 5.0,
        "seed": 2201,
        "C_mean": 0.4467203104809235,
        "C_std": 0.05913281735845282,
        "gamma_eff": 0.7324919796715745,
        "D_best": 0.21762659614715751,
        "D_best_std": 0.039553692942895374,
        "D_jade": 0.23299123345430636,
        "D_jade_std": 0.04339460688271364,
        "elapsed": 0.5912373065948486
      },
      {
        "n_S": 2,
        "n_E": 2,
        "d_S": 4,
        "d_E": 4,
        "d_total": 16,
        "coupling": "random",
        "realization": 1,
        "t": 10.0,
        "seed": 2201,
        "C_mean": 0.3607537484602228,
        "C_std": 0.07089316184297706,
        "gamma_eff": 0.8583346310007641,
        "D_best": 0.246217437291845,
        "D_best_std": 0.042211979942868086,
        "D_jade": 0.2887648252157743,
        "D_jade_std": 0.04280592350653991,
        "elapsed": 0.5894443988800049
      },
      {
        "n_S": 2,
        "n_E": 2,
        "d_S": 4,
        "d_E": 4,
        "d_total": 16,
        "coupling": "random",
        "realization": 1,
        "t": 20.0,
        "seed": 2201,
        "C_mean": 0.3623413226827485,
        "C_std": 0.0918758192207239,
        "gamma_eff": 0.885932656965925,
        "D_best": 0.2528416945014862,
        "D_best_std": 0.04339953319685438,
        "D_jade": 0.28345341069803637,
        "D_jade_std": 0.05614010105753777,
        "elapsed": 0.5926809310913086
      },
      {
        "n_S": 2,
        "n_E": 2,
        "d_S": 4,
        "d_E": 4,
        "d_total": 16,
        "coupling": "random",
        "realization": 2,
        "t": 5.0,
        "seed": 2202,
        "C_mean": 0.2869858518060419,
        "C_std": 0.10600937471483585,
        "gamma_eff": 0.9609058280844631,
        "D_best": 0.4104017782582438,
        "D_best_std": 0.0471833555297291,
        "D_jade": 0.457361913319167,
        "D_jade_std": 0.06508095639057512,
        "elapsed": 0.5878539085388184
      },
      {
        "n_S": 2,
        "n_E": 2,
        "d_S": 4,
        "d_E": 4,
        "d_total": 16,
        "coupling": "random",
        "realization": 2,
        "t": 10.0,
        "seed": 2202,
        "C_mean": 0.42234723597703727,
        "C_std": 0.07449338581064419,
        "gamma_eff": 0.7598937670011287,
        "D_best": 0.24774061849689763,
        "D_best_std": 0.033011660502791126,
        "D_jade": 0.2684904328255547,
        "D_jade_std": 0.037242982669691845,
        "elapsed": 0.591264009475708
      },
      {
        "n_S": 2,
        "n_E": 2,
        "d_S": 4,
        "d_E": 4,
        "d_total": 16,
        "coupling": "random",
        "realization": 2,
        "t": 20.0,
        "seed": 2202,
        "C_mean": 0.3917687622867901,
        "C_std": 0.07522486197983798,
        "gamma_eff": 0.8294233578638068,
        "D_best": 0.24889380701767877,
        "D_best_std": 0.04087418923094649,
        "D_jade": 0.2792789967628921,
        "D_jade_std": 0.04337617775986015,
        "elapsed": 0.5902905464172363
      },
      {
        "n_S": 2,
        "n_E": 3,
        "d_S": 4,
        "d_E": 8,
        "d_total": 32,
        "coupling": "local",
        "realization": 0,
        "t": 5.0,
        "seed": 2300,
        "C_mean": 0.23612125327044517,
        "C_std": 0.10113979816930382,
        "gamma_eff": 0.9899956200985516,
        "D_best": 0.39495466071177426,
        "D_best_std": 0.04258974507014109,
        "D_jade": 0.45284027599763305,
        "D_jade_std": 0.07217115692611131,
        "elapsed": 0.6644275188446045
      },
      {
        "n_S": 2,
        "n_E": 3,
        "d_S": 4,
        "d_E": 8,
        "d_total": 32,
        "coupling": "local",
        "realization": 0,
        "t": 10.0,
        "seed": 2300,
        "C_mean": 0.6338223949023473,
        "C_std": 0.04938519438053429,
        "gamma_eff": 0.48897806097015506,
        "D_best": 0.1600512051543011,
        "D_best_std": 0.023356277435703638,
        "D_jade": 0.18703502015720075,
        "D_jade_std": 0.03501997177063033,
        "elapsed": 0.6603236198425293
      },
      {
        "n_S": 2,
        "n_E": 3,
        "d_S": 4,
        "d_E": 8,
        "d_total": 32,
        "coupling": "local",
        "realization": 0,
        "t": 20.0,
        "seed": 2300,
        "C_mean": 0.3368852803763158,
        "C_std": 0.06424474276077634,
        "gamma_eff": 0.893730376875178,
        "D_best": 0.2250122954688451,
        "D_best_std": 0.04012670132058319,
        "D_jade": 0.27670800104283855,
        "D_jade_std": 0.036460320987115276,
        "elapsed": 0.6858687400817871
      },
      {
        "n_S": 2,
        "n_E": 3,
        "d_S": 4,
        "d_E": 8,
        "d_total": 32,
        "coupling": "random",
        "realization": 0,
        "t": 5.0,
        "seed": 2300,
        "C_mean": 0.29026464694024257,
        "C_std": 0.06299546370389608,
        "gamma_eff": 0.9467465673113561,
        "D_best": 0.25945953674380745,
        "D_best_std": 0.03364910678931851,
        "D_jade": 0.32565139325130643,
        "D_jade_std": 0.04899069597904217,
        "elapsed": 0.6821842193603516
      },
      {
        "n_S": 2,
        "n_E": 3,
        "d_S": 4,
        "d_E": 8,
        "d_total": 32,
        "coupling": "random",
        "realization": 0,
        "t": 10.0,
        "seed": 2300,
        "C_mean": 0.3507057393038775,
        "C_std": 0.05912926681634401,
        "gamma_eff": 0.8757185924933193,
        "D_best": 0.17530844695844816,
        "D_best_std": 0.03888686078902655,
        "D_jade": 0.2402073209098486,
        "D_jade_std": 0.019854363436940744,
        "elapsed": 0.6639444828033447
      },
      {
        "n_S": 2,
        "n_E": 3,
        "d_S": 4,
        "d_E": 8,
        "d_total": 32,
        "coupling": "random",
        "realization": 0,
        "t": 20.0,
        "seed": 2300,
        "C_mean": 0.3756067857810264,
        "C_std": 0.05521643868403651,
        "gamma_eff": 0.8344398108864786,
        "D_best": 0.18621624205292264,
        "D_best_std": 0.028240870213399605,
        "D_jade": 0.23293337495957586,
        "D_jade_std": 0.03040021045823111,
        "elapsed": 0.668353796005249
      },
      {
        "n_S": 2,
        "n_E": 3,
        "d_S": 4,
        "d_E": 8,
        "d_total": 32,
        "coupling": "random",
        "realization": 1,
        "t": 5.0,
        "seed": 2301,
        "C_mean": 0.27636959315396376,
        "C_std": 0.07100249797627808,
        "gamma_eff": 0.9778593042341917,
        "D_best": 0.22509270878532445,
        "D_best_std": 0.045257800071369855,
        "D_jade": 0.31537248625440406,
        "D_jade_std": 0.04705808622419156,
        "elapsed": 0.728672981262207
      },
      {
        "n_S": 2,
        "n_E": 3,
        "d_S": 4,
        "d_E": 8,
        "d_total": 32,
        "coupling": "random",
        "realization": 1,
        "t": 10.0,
        "seed": 2301,
        "C_mean": 0.45322394579054004,
        "C_std": 0.056556659815751135,
        "gamma_eff": 0.7281681582902743,
        "D_best": 0.14346567731394594,
        "D_best_std": 0.03454820822607438,
        "D_jade": 0.1585391363232846,
        "D_jade_std": 0.030530772912100317,
        "elapsed": 0.668787956237793
      },
      {
        "n_S": 2,
        "n_E": 3,
        "d_S": 4,
        "d_E": 8,
        "d_total": 32,
        "coupling": "random",
        "realization": 1,
        "t": 20.0,
        "seed": 2301,
        "C_mean": 0.34591459220185056,
        "C_std": 0.0567269132858174,
        "gamma_eff": 0.8570097151959364,
        "D_best": 0.19377013601053505,
        "D_best_std": 0.039579706696582555,
        "D_jade": 0.25497251703286833,
        "D_jade_std": 0.028121856327168113,
        "elapsed": 0.6866748332977295
      },
      {
        "n_S": 2,
        "n_E": 3,
        "d_S": 4,
        "d_E": 8,
        "d_total": 32,
        "coupling": "random",
        "realization": 2,
        "t": 5.0,
        "seed": 2302,
        "C_mean": 0.33057987846307896,
        "C_std": 0.06837296855656104,
        "gamma_eff": 0.8864332167193977,
        "D_best": 0.259282000805123,
        "D_best_std": 0.04362968309742225,
        "D_jade": 0.3063723918297418,
        "D_jade_std": 0.05095344722327562,
        "elapsed": 0.6688845157623291
      },
      {
        "n_S": 2,
        "n_E": 3,
        "d_S": 4,
        "d_E": 8,
        "d_total": 32,
        "coupling": "random",
        "realization": 2,
        "t": 10.0,
        "seed": 2302,
        "C_mean": 0.38322265151292173,
        "C_std": 0.0631966758917484,
        "gamma_eff": 0.8120196614966604,
        "D_best": 0.1987165185628659,
        "D_best_std": 0.033869950190731045,
        "D_jade": 0.23094565473646625,
        "D_jade_std": 0.04526523482654757,
        "elapsed": 0.6727068424224854
      },
      {
        "n_S": 2,
        "n_E": 3,
        "d_S": 4,
        "d_E": 8,
        "d_total": 32,
        "coupling": "random",
        "realization": 2,
        "t": 20.0,
        "seed": 2302,
        "C_mean": 0.3319572924767077,
        "C_std": 0.05539938092571777,
        "gamma_eff": 0.8769073063218235,
        "D_best": 0.19212405940803864,
        "D_best_std": 0.04024912107528216,
        "D_jade": 0.2652998566904887,
        "D_jade_std": 0.02861038849503775,
        "elapsed": 0.6786391735076904
      },
      {
        "n_S": 2,
        "n_E": 4,
        "d_S": 4,
        "d_E": 16,
        "d_total": 64,
        "coupling": "local",
        "realization": 0,
        "t": 5.0,
        "seed": 2400,
        "C_mean": 0.2512215921335238,
        "C_std": 0.10330763836318677,
        "gamma_eff": 1.0159439856439638,
        "D_best": 0.3974578337191993,
        "D_best_std": 0.04872600957186428,
        "D_jade": 0.45618698622126996,
        "D_jade_std": 0.07420578335537958,
        "elapsed": 0.8180322647094727
      },
      {
        "n_S": 2,
        "n_E": 4,
        "d_S": 4,
        "d_E": 16,
        "d_total": 64,
        "coupling": "local",
        "realization": 0,
        "t": 10.0,
        "seed": 2400,
        "C_mean": 0.6241089580869006,
        "C_std": 0.038594252316237886,
        "gamma_eff": 0.5000531891032578,
        "D_best": 0.18817790533193304,
        "D_best_std": 0.021794502324984092,
        "D_jade": 0.2078910170685981,
        "D_jade_std": 0.02669228258859342,
        "elapsed": 0.8433055877685547
      },
      {
        "n_S": 2,
        "n_E": 4,
        "d_S": 4,
        "d_E": 16,
        "d_total": 64,
        "coupling": "local",
        "realization": 0,
        "t": 20.0,
        "seed": 2400,
        "C_mean": 0.3695216199351083,
        "C_std": 0.05083550745260551,
        "gamma_eff": 0.82840272708793,
        "D_best": 0.17732808145089274,
        "D_best_std": 0.03497231168738119,
        "D_jade": 0.2312130288978102,
        "D_jade_std": 0.030156978681172803,
        "elapsed": 0.8209972381591797
      },
      {
        "n_S": 2,
        "n_E": 4,
        "d_S": 4,
        "d_E": 16,
        "d_total": 64,
        "coupling": "random",
        "realization": 0,
        "t": 5.0,
        "seed": 2400,
        "C_mean": 0.2906854605538508,
        "C_std": 0.044673252332645665,
        "gamma_eff": 0.9435754363415038,
        "D_best": 0.19404497099664864,
        "D_best_std": 0.03385720311841844,
        "D_jade": 0.2797016012807816,
        "D_jade_std": 0.03695436246245429,
        "elapsed": 0.8211438655853271
      },
      {
        "n_S": 2,
        "n_E": 4,
        "d_S": 4,
        "d_E": 16,
        "d_total": 64,
        "coupling": "random",
        "realization": 0,
        "t": 10.0,
        "seed": 2400,
        "C_mean": 0.29524873314333283,
        "C_std": 0.03689664442600875,
        "gamma_eff": 0.9087089562402758,
        "D_best": 0.12542513668479482,
        "D_best_std": 0.023496062500167524,
        "D_jade": 0.2460421642249282,
        "D_jade_std": 0.02844124620302405,
        "elapsed": 0.8504946231842041
      },
      {
        "n_S": 2,
        "n_E": 4,
        "d_S": 4,
        "d_E": 16,
        "d_total": 64,
        "coupling": "random",
        "realization": 0,
        "t": 20.0,
        "seed": 2400,
        "C_mean": 0.2684622940198311,
        "C_std": 0.04091583452391198,
        "gamma_eff": 0.9705912204924493,
        "D_best": 0.13583050846450523,
        "D_best_std": 0.044133525642929314,
        "D_jade": 0.2813413952855835,
        "D_jade_std": 0.023236300302707482,
        "elapsed": 0.8348705768585205
      },
      {
        "n_S": 2,
        "n_E": 4,
        "d_S": 4,
        "d_E": 16,
        "d_total": 64,
        "coupling": "random",
        "realization": 1,
        "t": 5.0,
        "seed": 2401,
        "C_mean": 0.24534542436949752,
        "C_std": 0.058669025934515055,
        "gamma_eff": 0.994060277958465,
        "D_best": 0.2319062030218665,
        "D_best_std": 0.04145681456800588,
        "D_jade": 0.32251042434889304,
        "D_jade_std": 0.04628981695214715,
        "elapsed": 0.8382220268249512
      },
      {
        "n_S": 2,
        "n_E": 4,
        "d_S": 4,
        "d_E": 16,
        "d_total": 64,
        "coupling": "random",
        "realization": 1,
        "t": 10.0,
        "seed": 2401,
        "C_mean": 0.3263328786539146,
        "C_std": 0.037432393949036316,
        "gamma_eff": 0.8946458440112156,
        "D_best": 0.11710112884419133,
        "D_best_std": 0.025935881518847837,
        "D_jade": 0.21911214844423335,
        "D_jade_std": 0.025047653591486998,
        "elapsed": 0.8611762523651123
      },
      {
        "n_S": 2,
        "n_E": 4,
        "d_S": 4,
        "d_E": 16,
        "d_total": 64,
        "coupling": "random",
        "realization": 1,
        "t": 20.0,
        "seed": 2401,
        "C_mean": 0.3352422240409049,
        "C_std": 0.05020477558034231,
        "gamma_eff": 0.8762285992941298,
        "D_best": 0.14118937607765933,
        "D_best_std": 0.03662183701359611,
        "D_jade": 0.22436024242788213,
        "D_jade_std": 0.025948840587503665,
        "elapsed": 0.8516898155212402
      },
      {
        "n_S": 2,
        "n_E": 4,
        "d_S": 4,
        "d_E": 16,
        "d_total": 64,
        "coupling": "random",
        "realization": 2,
        "t": 5.0,
        "seed": 2402,
        "C_mean": 0.25778701971482026,
        "C_std": 0.04820271626627358,
        "gamma_eff": 0.9774555142619717,
        "D_best": 0.17169569655596512,
        "D_best_std": 0.03435430733303733,
        "D_jade": 0.29293203934715073,
        "D_jade_std": 0.042455152778269514,
        "elapsed": 0.8433313369750977
      },
      {
        "n_S": 2,
        "n_E": 4,
        "d_S": 4,
        "d_E": 16,
        "d_total": 64,
        "coupling": "random",
        "realization": 2,
        "t": 10.0,
        "seed": 2402,
        "C_mean": 0.30633563731135366,
        "C_std": 0.029232624384575138,
        "gamma_eff": 0.9259906683402788,
        "D_best": 0.10372455401418834,
        "D_best_std": 0.023671810375071666,
        "D_jade": 0.23510256707419935,
        "D_jade_std": 0.024687930368060298,
        "elapsed": 0.8267173767089844
      },
      {
        "n_S": 2,
        "n_E": 4,
        "d_S": 4,
        "d_E": 16,
        "d_total": 64,
        "coupling": "random",
        "realization": 2,
        "t": 20.0,
        "seed": 2402,
        "C_mean": 0.30869439891142014,
        "C_std": 0.039249725134432895,
        "gamma_eff": 0.9284942595040994,
        "D_best": 0.10936480801708388,
        "D_best_std": 0.027503883109279457,
        "D_jade": 0.23628612442142413,
        "D_jade_std": 0.02186890161254083,
        "elapsed": 0.8245806694030762
      },
      {
        "n_S": 2,
        "n_E": 5,
        "d_S": 4,
        "d_E": 32,
        "d_total": 128,
        "coupling": "local",
        "realization": 0,
        "t": 5.0,
        "seed": 2500,
        "C_mean": 0.24096602996905397,
        "C_std": 0.10074698081349268,
        "gamma_eff": 1.0282139420835235,
        "D_best": 0.3951087356983657,
        "D_best_std": 0.04346338740158285,
        "D_jade": 0.4620553493716326,
        "D_jade_std": 0.07452121272719536,
        "elapsed": 1.0887601375579834
      },
      {
        "n_S": 2,
        "n_E": 5,
        "d_S": 4,
        "d_E": 32,
        "d_total": 128,
        "coupling": "local",
        "realization": 0,
        "t": 10.0,
        "seed": 2500,
        "C_mean": 0.6316479230288901,
        "C_std": 0.04724898344467816,
        "gamma_eff": 0.500585666982185,
        "D_best": 0.18969561698156365,
        "D_best_std": 0.024513507883355747,
        "D_jade": 0.21134975406934625,
        "D_jade_std": 0.03091506790434387,
        "elapsed": 1.0811917781829834
      },
      {
        "n_S": 2,
        "n_E": 5,
        "d_S": 4,
        "d_E": 32,
        "d_total": 128,
        "coupling": "local",
        "realization": 0,
        "t": 20.0,
        "seed": 2500,
        "C_mean": 0.4010238966583854,
        "C_std": 0.06065288441924928,
        "gamma_eff": 0.7888100705826444,
        "D_best": 0.23272811593183357,
        "D_best_std": 0.03754111830964132,
        "D_jade": 0.25987793275427384,
        "D_jade_std": 0.03991831969696137,
        "elapsed": 1.0719232559204102
      },
      {
        "n_S": 2,
        "n_E": 5,
        "d_S": 4,
        "d_E": 32,
        "d_total": 128,
        "coupling": "random",
        "realization": 0,
        "t": 5.0,
        "seed": 2500,
        "C_mean": 0.26971723817612103,
        "C_std": 0.03917097430406271,
        "gamma_eff": 0.9684812777248007,
        "D_best": 0.13662718913296215,
        "D_best_std": 0.028314282384615166,
        "D_jade": 0.2725357921552017,
        "D_jade_std": 0.03399541403216489,
        "elapsed": 1.0916564464569092
      },
      {
        "n_S": 2,
        "n_E": 5,
        "d_S": 4,
        "d_E": 32,
        "d_total": 128,
        "coupling": "random",
        "realization": 0,
        "t": 10.0,
        "seed": 2500,
        "C_mean": 0.3219201304733791,
        "C_std": 0.023462640025343342,
        "gamma_eff": 0.9022382892519311,
        "D_best": 0.07106835135606362,
        "D_best_std": 0.024616166408565333,
        "D_jade": 0.21036632988627868,
        "D_jade_std": 0.01905802506688761,
        "elapsed": 1.0800890922546387
      },
      {
        "n_S": 2,
        "n_E": 5,
        "d_S": 4,
        "d_E": 32,
        "d_total": 128,
        "coupling": "random",
        "realization": 0,
        "t": 20.0,
        "seed": 2500,
        "C_mean": 0.29137781537031016,
        "C_std": 0.027324050102526958,
        "gamma_eff": 0.9444124218632938,
        "D_best": 0.09391737010905965,
        "D_best_std": 0.03155091147526344,
        "D_jade": 0.2453765509241788,
        "D_jade_std": 0.021891813135113576,
        "elapsed": 1.1010732650756836
      },
      {
        "n_S": 2,
        "n_E": 5,
        "d_S": 4,
        "d_E": 32,
        "d_total": 128,
        "coupling": "random",
        "realization": 1,
        "t": 5.0,
        "seed": 2501,
        "C_mean": 0.2823325751465689,
        "C_std": 0.0718664872414066,
        "gamma_eff": 0.9369822360010271,
        "D_best": 0.2690860092294311,
        "D_best_std": 0.04601957941227347,
        "D_jade": 0.33122767629038036,
        "D_jade_std": 0.06191845201814217,
        "elapsed": 1.0746808052062988
      },
      {
        "n_S": 2,
        "n_E": 5,
        "d_S": 4,
        "d_E": 32,
        "d_total": 128,
        "coupling": "random",
        "realization": 1,
        "t": 10.0,
        "seed": 2501,
        "C_mean": 0.3624994723231885,
        "C_std": 0.04427669587612823,
        "gamma_eff": 0.8528042729856655,
        "D_best": 0.131359178226379,
        "D_best_std": 0.02551728427562263,
        "D_jade": 0.19187916636751262,
        "D_jade_std": 0.028341788202700547,
        "elapsed": 1.0816802978515625
      },
      {
        "n_S": 2,
        "n_E": 5,
        "d_S": 4,
        "d_E": 32,
        "d_total": 128,
        "coupling": "random",
        "realization": 1,
        "t": 20.0,
        "seed": 2501,
        "C_mean": 0.30193328726875,
        "C_std": 0.03662199007433851,
        "gamma_eff": 0.9310436975926231,
        "D_best": 0.09661659708503927,
        "D_best_std": 0.034126262234816324,
        "D_jade": 0.23738508044123566,
        "D_jade_std": 0.022994931753597295,
        "elapsed": 1.0751709938049316
      },
      {
        "n_S": 2,
        "n_E": 5,
        "d_S": 4,
        "d_E": 32,
        "d_total": 128,
        "coupling": "random",
        "realization": 2,
        "t": 5.0,
        "seed": 2502,
        "C_mean": 0.2796593885164262,
        "C_std": 0.04575937812059497,
        "gamma_eff": 0.9626784779770606,
        "D_best": 0.16146449938594884,
        "D_best_std": 0.036394459528356335,
        "D_jade": 0.2795011005103618,
        "D_jade_std": 0.040773697896932595,
        "elapsed": 1.0684490203857422
      },
      {
        "n_S": 2,
        "n_E": 5,
        "d_S": 4,
        "d_E": 32,
        "d_total": 128,
        "coupling": "random",
        "realization": 2,
        "t": 10.0,
        "seed": 2502,
        "C_mean": 0.2895924150266762,
        "C_std": 0.028560864181294807,
        "gamma_eff": 0.9417386166837426,
        "D_best": 0.09625041494216116,
        "D_best_std": 0.02506446337536276,
        "D_jade": 0.2466472995897179,
        "D_jade_std": 0.022834259654684025,
        "elapsed": 1.081202745437622
      },
      {
        "n_S": 2,
        "n_E": 5,
        "d_S": 4,
        "d_E": 32,
        "d_total": 128,
        "coupling": "random",
        "realization": 2,
        "t": 20.0,
        "seed": 2502,
        "C_mean": 0.28153725137725233,
        "C_std": 0.03542197542215284,
        "gamma_eff": 0.9550451684617007,
        "D_best": 0.09855868629879065,
        "D_best_std": 0.029697916130735715,
        "D_jade": 0.2562785522773626,
        "D_jade_std": 0.026135873129285166,
        "elapsed": 1.1060099601745605
      },
      {
        "n_S": 2,
        "n_E": 6,
        "d_S": 4,
        "d_E": 64,
        "d_total": 256,
        "coupling": "local",
        "realization": 0,
        "t": 5.0,
        "seed": 2600,
        "C_mean": 0.24433025736433941,
        "C_std": 0.09938181776209874,
        "gamma_eff": 1.030060843757237,
        "D_best": 0.39741941270318776,
        "D_best_std": 0.047911557446031976,
        "D_jade": 0.4524693695666573,
        "D_jade_std": 0.07667440470020057,
        "elapsed": 1.766122817993164
      },
      {
        "n_S": 2,
        "n_E": 6,
        "d_S": 4,
        "d_E": 64,
        "d_total": 256,
        "coupling": "local",
        "realization": 0,
        "t": 10.0,
        "seed": 2600,
        "C_mean": 0.6264002918205357,
        "C_std": 0.04424291572069979,
        "gamma_eff": 0.4989753933073742,
        "D_best": 0.19080627033363742,
        "D_best_std": 0.023787084731113198,
        "D_jade": 0.21356753445482307,
        "D_jade_std": 0.0292493103272167,
        "elapsed": 1.818272352218628
      },
      {
        "n_S": 2,
        "n_E": 6,
        "d_S": 4,
        "d_E": 64,
        "d_total": 256,
        "coupling": "local",
        "realization": 0,
        "t": 20.0,
        "seed": 2600,
        "C_mean": 0.38825585977537286,
        "C_std": 0.0665768737917008,
        "gamma_eff": 0.8262287243228835,
        "D_best": 0.21631360083995127,
        "D_best_std": 0.035617675885110986,
        "D_jade": 0.24956243470373202,
        "D_jade_std": 0.035612351091580306,
        "elapsed": 1.7723956108093262
      },
      {
        "n_S": 2,
        "n_E": 6,
        "d_S": 4,
        "d_E": 64,
        "d_total": 256,
        "coupling": "random",
        "realization": 0,
        "t": 5.0,
        "seed": 2600,
        "C_mean": 0.27954955475512283,
        "C_std": 0.05804708645965157,
        "gamma_eff": 0.9629816800258926,
        "D_best": 0.22011821506063037,
        "D_best_std": 0.034764988648017595,
        "D_jade": 0.31149039715158117,
        "D_jade_std": 0.04385840796614338,
        "elapsed": 1.791666030883789
      },
      {
        "n_S": 2,
        "n_E": 6,
        "d_S": 4,
        "d_E": 64,
        "d_total": 256,
        "coupling": "random",
        "realization": 0,
        "t": 10.0,
        "seed": 2600,
        "C_mean": 0.32187663599157806,
        "C_std": 0.027158549855218202,
        "gamma_eff": 0.9086992476110484,
        "D_best": 0.08429381294240429,
        "D_best_std": 0.029777199315129056,
        "D_jade": 0.21331847847395288,
        "D_jade_std": 0.020326676611275917,
        "elapsed": 1.808779001235962
      },
      {
        "n_S": 2,
        "n_E": 6,
        "d_S": 4,
        "d_E": 64,
        "d_total": 256,
        "coupling": "random",
        "realization": 0,
        "t": 20.0,
        "seed": 2600,
        "C_mean": 0.2758991842789022,
        "C_std": 0.024467316411637515,
        "gamma_eff": 0.9576857120327577,
        "D_best": 0.0748639662007441,
        "D_best_std": 0.02942472225244795,
        "D_jade": 0.2550261425132264,
        "D_jade_std": 0.01936708330494455,
        "elapsed": 1.7885901927947998
      },
      {
        "n_S": 2,
        "n_E": 6,
        "d_S": 4,
        "d_E": 64,
        "d_total": 256,
        "coupling": "random",
        "realization": 1,
        "t": 5.0,
        "seed": 2601,
        "C_mean": 0.27874531168620637,
        "C_std": 0.05627555584249877,
        "gamma_eff": 0.9644349949244108,
        "D_best": 0.22714357376002062,
        "D_best_std": 0.03251595868082852,
        "D_jade": 0.30446783580940684,
        "D_jade_std": 0.04143772911982356,
        "elapsed": 1.803971767425537
      },
      {
        "n_S": 2,
        "n_E": 6,
        "d_S": 4,
        "d_E": 64,
        "d_total": 256,
        "coupling": "random",
        "realization": 1,
        "t": 10.0,
        "seed": 2601,
        "C_mean": 0.3215835180384407,
        "C_std": 0.023194941619946497,
        "gamma_eff": 0.907560395445242,
        "D_best": 0.09254587323739681,
        "D_best_std": 0.029506057040266535,
        "D_jade": 0.2172564076258764,
        "D_jade_std": 0.01820803543614771,
        "elapsed": 1.8001623153686523
      },
      {
        "n_S": 2,
        "n_E": 6,
        "d_S": 4,
        "d_E": 64,
        "d_total": 256,
        "coupling": "random",
        "realization": 1,
        "t": 20.0,
        "seed": 2601,
        "C_mean": 0.280870622032845,
        "C_std": 0.02473921289315396,
        "gamma_eff": 0.956375752540823,
        "D_best": 0.08024702537579735,
        "D_best_std": 0.030583556020950146,
        "D_jade": 0.2535166257816159,
        "D_jade_std": 0.020923873919291337,
        "elapsed": 1.8140673637390137
      },
      {
        "n_S": 2,
        "n_E": 6,
        "d_S": 4,
        "d_E": 64,
        "d_total": 256,
        "coupling": "random",
        "realization": 2,
        "t": 5.0,
        "seed": 2602,
        "C_mean": 0.2646726796039655,
        "C_std": 0.06268823980761304,
        "gamma_eff": 0.9772617288255709,
        "D_best": 0.2063805980295045,
        "D_best_std": 0.03778540869452266,
        "D_jade": 0.2895130536943963,
        "D_jade_std": 0.05622302460870226,
        "elapsed": 1.8066012859344482
      },
      {
        "n_S": 2,
        "n_E": 6,
        "d_S": 4,
        "d_E": 64,
        "d_total": 256,
        "coupling": "random",
        "realization": 2,
        "t": 10.0,
        "seed": 2602,
        "C_mean": 0.33442525924352284,
        "C_std": 0.028272296078135493,
        "gamma_eff": 0.8885085443392761,
        "D_best": 0.09035997177743539,
        "D_best_std": 0.022800770816668554,
        "D_jade": 0.20276099469123485,
        "D_jade_std": 0.023803792401753208,
        "elapsed": 1.796724796295166
      },
      {
        "n_S": 2,
        "n_E": 6,
        "d_S": 4,
        "d_E": 64,
        "d_total": 256,
        "coupling": "random",
        "realization": 2,
        "t": 20.0,
        "seed": 2602,
        "C_mean": 0.28881842332874924,
        "C_std": 0.023672723219502673,
        "gamma_eff": 0.9527408926604436,
        "D_best": 0.07896756684984302,
        "D_best_std": 0.029576854113371385,
        "D_jade": 0.24472318725507797,
        "D_jade_std": 0.020833458228733222,
        "elapsed": 1.7991838455200195
      },
      {
        "n_S": 2,
        "n_E": 7,
        "d_S": 4,
        "d_E": 128,
        "d_total": 512,
        "coupling": "local",
        "realization": 0,
        "t": 5.0,
        "seed": 2700,
        "C_mean": 0.24013331588242018,
        "C_std": 0.1009155460937881,
        "gamma_eff": 1.0149624766563954,
        "D_best": 0.39702405631294424,
        "D_best_std": 0.044085709227778075,
        "D_jade": 0.450652925785612,
        "D_jade_std": 0.07714192552834316,
        "elapsed": 3.275073766708374
      },
      {
        "n_S": 2,
        "n_E": 7,
        "d_S": 4,
        "d_E": 128,
        "d_total": 512,
        "coupling": "local",
        "realization": 0,
        "t": 10.0,
        "seed": 2700,
        "C_mean": 0.6261589264412528,
        "C_std": 0.04285441540743655,
        "gamma_eff": 0.4927866404171075,
        "D_best": 0.19569822529620384,
        "D_best_std": 0.02322930449512369,
        "D_jade": 0.21032131439302248,
        "D_jade_std": 0.03060168849929315,
        "elapsed": 3.2295002937316895
      },
      {
        "n_S": 2,
        "n_E": 7,
        "d_S": 4,
        "d_E": 128,
        "d_total": 512,
        "coupling": "local",
        "realization": 0,
        "t": 20.0,
        "seed": 2700,
        "C_mean": 0.38597499863934176,
        "C_std": 0.05723217576491406,
        "gamma_eff": 0.8162876199572887,
        "D_best": 0.22452103574769972,
        "D_best_std": 0.034744663079736,
        "D_jade": 0.2546589118000433,
        "D_jade_std": 0.03638504142953006,
        "elapsed": 3.2219276428222656
      },
      {
        "n_S": 2,
        "n_E": 7,
        "d_S": 4,
        "d_E": 128,
        "d_total": 512,
        "coupling": "random",
        "realization": 0,
        "t": 5.0,
        "seed": 2700,
        "C_mean": 0.26834592232851,
        "C_std": 0.06183280486764533,
        "gamma_eff": 0.9628387751508994,
        "D_best": 0.20510212900015964,
        "D_best_std": 0.04020557927196668,
        "D_jade": 0.29115397634828893,
        "D_jade_std": 0.045665843027005715,
        "elapsed": 3.029080867767334
      },
      {
        "n_S": 2,
        "n_E": 7,
        "d_S": 4,
        "d_E": 128,
        "d_total": 512,
        "coupling": "random",
        "realization": 0,
        "t": 10.0,
        "seed": 2700,
        "C_mean": 0.33860778156361804,
        "C_std": 0.028658001956872195,
        "gamma_eff": 0.8750867172394948,
        "D_best": 0.08557371658606819,
        "D_best_std": 0.025443428075541882,
        "D_jade": 0.19630976050088095,
        "D_jade_std": 0.0222259235989059,
        "elapsed": 2.96496319770813
      },
      {
        "n_S": 2,
        "n_E": 7,
        "d_S": 4,
        "d_E": 128,
        "d_total": 512,
        "coupling": "random",
        "realization": 0,
        "t": 20.0,
        "seed": 2700,
        "C_mean": 0.2922910377593641,
        "C_std": 0.022541649729868222,
        "gamma_eff": 0.9390153254409195,
        "D_best": 0.07083257257280434,
        "D_best_std": 0.02752882169860295,
        "D_jade": 0.23867093795701508,
        "D_jade_std": 0.016611647611593578,
        "elapsed": 2.9020235538482666
      },
      {
        "n_S": 2,
        "n_E": 7,
        "d_S": 4,
        "d_E": 128,
        "d_total": 512,
        "coupling": "random",
        "realization": 1,
        "t": 5.0,
        "seed": 2701,
        "C_mean": 0.2764917170678889,
        "C_std": 0.05154211535517177,
        "gamma_eff": 0.9548129002537954,
        "D_best": 0.1751137990235365,
        "D_best_std": 0.037404296192684434,
        "D_jade": 0.27965884373646577,
        "D_jade_std": 0.04220719164546377,
        "elapsed": 3.090618848800659
      },
      {
        "n_S": 2,
        "n_E": 7,
        "d_S": 4,
        "d_E": 128,
        "d_total": 512,
        "coupling": "random",
        "realization": 1,
        "t": 10.0,
        "seed": 2701,
        "C_mean": 0.3093118421961465,
        "C_std": 0.02280316532811454,
        "gamma_eff": 0.910581938494925,
        "D_best": 0.06990392187214203,
        "D_best_std": 0.02494294342901392,
        "D_jade": 0.22104138432496775,
        "D_jade_std": 0.02016034894047761,
        "elapsed": 3.030463695526123
      },
      {
        "n_S": 2,
        "n_E": 7,
        "d_S": 4,
        "d_E": 128,
        "d_total": 512,
        "coupling": "random",
        "realization": 1,
        "t": 20.0,
        "seed": 2701,
        "C_mean": 0.27427634605798556,
        "C_std": 0.02121330228439757,
        "gamma_eff": 0.9635954687974432,
        "D_best": 0.06468936293009807,
        "D_best_std": 0.025056013602648794,
        "D_jade": 0.2541032645494314,
        "D_jade_std": 0.020258875435869395,
        "elapsed": 3.0945606231689453
      },
      {
        "n_S": 2,
        "n_E": 7,
        "d_S": 4,
        "d_E": 128,
        "d_total": 512,
        "coupling": "random",
        "realization": 2,
        "t": 5.0,
        "seed": 2702,
        "C_mean": 0.275015617115749,
        "C_std": 0.054866055271796825,
        "gamma_eff": 0.9596188277226355,
        "D_best": 0.21156909092454965,
        "D_best_std": 0.04241862947761683,
        "D_jade": 0.28825160195497945,
        "D_jade_std": 0.05202772765652898,
        "elapsed": 3.1617400646209717
      },
      {
        "n_S": 2,
        "n_E": 7,
        "d_S": 4,
        "d_E": 128,
        "d_total": 512,
        "coupling": "random",
        "realization": 2,
        "t": 10.0,
        "seed": 2702,
        "C_mean": 0.3162153983083995,
        "C_std": 0.025267348311214213,
        "gamma_eff": 0.9161324162635035,
        "D_best": 0.08900343542574934,
        "D_best_std": 0.02753274940666234,
        "D_jade": 0.21893161559167282,
        "D_jade_std": 0.02161368903141826,
        "elapsed": 2.9830687046051025
      },
      {
        "n_S": 2,
        "n_E": 7,
        "d_S": 4,
        "d_E": 128,
        "d_total": 512,
        "coupling": "random",
        "realization": 2,
        "t": 20.0,
        "seed": 2702,
        "C_mean": 0.27215978201067836,
        "C_std": 0.023121816760612163,
        "gamma_eff": 0.9700560862171047,
        "D_best": 0.06792228326758804,
        "D_best_std": 0.029530156300546725,
        "D_jade": 0.25719418796011617,
        "D_jade_std": 0.019918828875568093,
        "elapsed": 3.142235517501831
      },
      {
        "n_S": 2,
        "n_E": 8,
        "d_S": 4,
        "d_E": 256,
        "d_total": 1024,
        "coupling": "local",
        "realization": 0,
        "t": 5.0,
        "seed": 2800,
        "C_mean": 0.24273142311520915,
        "C_std": 0.09894017117434557,
        "gamma_eff": 1.050395023238533,
        "D_best": 0.39836094516132303,
        "D_best_std": 0.03959464287220854,
        "D_jade": 0.46280975820454984,
        "D_jade_std": 0.07614002315210965,
        "elapsed": 8.24786376953125
      },
      {
        "n_S": 2,
        "n_E": 8,
        "d_S": 4,
        "d_E": 256,
        "d_total": 1024,
        "coupling": "local",
        "realization": 0,
        "t": 10.0,
        "seed": 2800,
        "C_mean": 0.6263157772577772,
        "C_std": 0.044837403859152095,
        "gamma_eff": 0.4894449201158409,
        "D_best": 0.19388083950348559,
        "D_best_std": 0.02490423024713537,
        "D_jade": 0.21301158760668507,
        "D_jade_std": 0.032132841098462116,
        "elapsed": 8.134819507598877
      },
      {
        "n_S": 2,
        "n_E": 8,
        "d_S": 4,
        "d_E": 256,
        "d_total": 1024,
        "coupling": "local",
        "realization": 0,
        "t": 20.0,
        "seed": 2800,
        "C_mean": 0.3824526414692093,
        "C_std": 0.05463012420906232,
        "gamma_eff": 0.8207203535552384,
        "D_best": 0.2203201374079477,
        "D_best_std": 0.03793765044749976,
        "D_jade": 0.25819490387359084,
        "D_jade_std": 0.03378543186055275,
        "elapsed": 8.071759462356567
      },
      {
        "n_S": 2,
        "n_E": 8,
        "d_S": 4,
        "d_E": 256,
        "d_total": 1024,
        "coupling": "random",
        "realization": 0,
        "t": 5.0,
        "seed": 2800,
        "C_mean": 0.27030850530736283,
        "C_std": 0.056944417064790316,
        "gamma_eff": 0.9724430836609468,
        "D_best": 0.1920236781992384,
        "D_best_std": 0.027747067193533224,
        "D_jade": 0.28970228841019946,
        "D_jade_std": 0.043454363016195915,
        "elapsed": 8.17228364944458
      },
      {
        "n_S": 2,
        "n_E": 8,
        "d_S": 4,
        "d_E": 256,
        "d_total": 1024,
        "coupling": "random",
        "realization": 0,
        "t": 10.0,
        "seed": 2800,
        "C_mean": 0.30808278042521237,
        "C_std": 0.01906448538834938,
        "gamma_eff": 0.9308808996748027,
        "D_best": 0.06607611668329988,
        "D_best_std": 0.02848826146461981,
        "D_jade": 0.22532082772402778,
        "D_jade_std": 0.014141856871600543,
        "elapsed": 8.13114881515503
      },
      {
        "n_S": 2,
        "n_E": 8,
        "d_S": 4,
        "d_E": 256,
        "d_total": 1024,
        "coupling": "random",
        "realization": 0,
        "t": 20.0,
        "seed": 2800,
        "C_mean": 0.27253499348760646,
        "C_std": 0.016401094593196205,
        "gamma_eff": 0.9738554906049774,
        "D_best": 0.056214655565386566,
        "D_best_std": 0.02745021603491883,
        "D_jade": 0.2546462300968679,
        "D_jade_std": 0.016263791725989397,
        "elapsed": 8.067476987838745
      },
      {
        "n_S": 2,
        "n_E": 8,
        "d_S": 4,
        "d_E": 256,
        "d_total": 1024,
        "coupling": "random",
        "realization": 1,
        "t": 5.0,
        "seed": 2801,
        "C_mean": 0.2731345541993391,
        "C_std": 0.041249365169057924,
        "gamma_eff": 0.9697552565227682,
        "D_best": 0.1411129563335048,
        "D_best_std": 0.027149306706300835,
        "D_jade": 0.27308100499454635,
        "D_jade_std": 0.03559944140450978,
        "elapsed": 8.164973735809326
      },
      {
        "n_S": 2,
        "n_E": 8,
        "d_S": 4,
        "d_E": 256,
        "d_total": 1024,
        "coupling": "random",
        "realization": 1,
        "t": 10.0,
        "seed": 2801,
        "C_mean": 0.3064685425354311,
        "C_std": 0.01894243521771943,
        "gamma_eff": 0.9202439820920807,
        "D_best": 0.05705423869531947,
        "D_best_std": 0.02484148487272962,
        "D_jade": 0.22318484796710458,
        "D_jade_std": 0.01844191746353812,
        "elapsed": 8.051133871078491
      },
      {
        "n_S": 2,
        "n_E": 8,
        "d_S": 4,
        "d_E": 256,
        "d_total": 1024,
        "coupling": "random",
        "realization": 1,
        "t": 20.0,
        "seed": 2801,
        "C_mean": 0.27229756949655004,
        "C_std": 0.01713981461464497,
        "gamma_eff": 0.9682174060205769,
        "D_best": 0.052684244480267296,
        "D_best_std": 0.026137965271405626,
        "D_jade": 0.2562744878474132,
        "D_jade_std": 0.015781697688325217,
        "elapsed": 8.235913515090942
      },
      {
        "n_S": 2,
        "n_E": 8,
        "d_S": 4,
        "d_E": 256,
        "d_total": 1024,
        "coupling": "random",
        "realization": 2,
        "t": 5.0,
        "seed": 2802,
        "C_mean": 0.26095697961400255,
        "C_std": 0.0652710112785814,
        "gamma_eff": 0.9734795337606812,
        "D_best": 0.2388619315197297,
        "D_best_std": 0.033521613044863244,
        "D_jade": 0.3145604109029694,
        "D_jade_std": 0.053392198986334856,
        "elapsed": 8.053213357925415
      },
      {
        "n_S": 2,
        "n_E": 8,
        "d_S": 4,
        "d_E": 256,
        "d_total": 1024,
        "coupling": "random",
        "realization": 2,
        "t": 10.0,
        "seed": 2802,
        "C_mean": 0.3068448741530804,
        "C_std": 0.02400163568242869,
        "gamma_eff": 0.9269018031162425,
        "D_best": 0.08623299033184857,
        "D_best_std": 0.023845280508387683,
        "D_jade": 0.22631968645361172,
        "D_jade_std": 0.02331871350753706,
        "elapsed": 8.093275785446167
      },
      {
        "n_S": 2,
        "n_E": 8,
        "d_S": 4,
        "d_E": 256,
        "d_total": 1024,
        "coupling": "random",
        "realization": 2,
        "t": 20.0,
        "seed": 2802,
        "C_mean": 0.27828563054355404,
        "C_std": 0.02503120206972247,
        "gamma_eff": 0.9606318478793384,
        "D_best": 0.07158450133454,
        "D_best_std": 0.03293807310160706,
        "D_jade": 0.25283365751179904,
        "D_jade_std": 0.019789458141538957,
        "elapsed": 7.92353081703186
      },
      {
        "n_S": 2,
        "n_E": 9,
        "d_S": 4,
        "d_E": 512,
        "d_total": 2048,
        "coupling": "local",
        "realization": 0,
        "t": 5.0,
        "seed": 2900,
        "C_mean": 0.2360727465639429,
        "C_std": 0.09587919355584999,
        "gamma_eff": 1.0130168614530926,
        "D_best": 0.3935472843923364,
        "D_best_std": 0.04495634805222926,
        "D_jade": 0.4554048702828837,
        "D_jade_std": 0.0731178919615819,
        "elapsed": 89.87538552284241
      },
      {
        "n_S": 2,
        "n_E": 9,
        "d_S": 4,
        "d_E": 512,
        "d_total": 2048,
        "coupling": "local",
        "realization": 0,
        "t": 10.0,
        "seed": 2900,
        "C_mean": 0.6301315997478437,
        "C_std": 0.04794447379121375,
        "gamma_eff": 0.5035792045546614,
        "D_best": 0.1916922256887608,
        "D_best_std": 0.025027371658461098,
        "D_jade": 0.212685994443227,
        "D_jade_std": 0.029253872198819576,
        "elapsed": 89.80397272109985
      },
      {
        "n_S": 2,
        "n_E": 9,
        "d_S": 4,
        "d_E": 512,
        "d_total": 2048,
        "coupling": "local",
        "realization": 0,
        "t": 20.0,
        "seed": 2900,
        "C_mean": 0.3886305163033728,
        "C_std": 0.06041919541732772,
        "gamma_eff": 0.8135676852636567,
        "D_best": 0.22089281534261404,
        "D_best_std": 0.03462282940112819,
        "D_jade": 0.2626028801169238,
        "D_jade_std": 0.03456986491451328,
        "elapsed": 91.16007685661316
      }
    ]
  }
}